git_feature-0.1.1.dist-info/METADATA
git_feature-0.1.1.dist-info/RECORD
git_feature-0.1.1.dist-info/WHEEL
git_feature-0.1.1.dist-info/entry_points.txt
git_feature-0.1.1.dist-info/top_level.txt
onnx_git_feature/__init__.py
onnx_git_feature/__main__.py
